ignite_travel/__init__.py
ignite_travel/sdk/__init__.py
ignite_travel/sdk/client.py
ignite_travel/sdk/entities.py
ignite_travel-0.1.18.dist-info/METADATA
ignite_travel-0.1.18.dist-info/WHEEL
ignite_travel-0.1.18.dist-info/top_level.txt
ignite_travel-0.1.18.dist-info/RECORD
