Metadata-Version: 2.4
Name: ignite-travel
Version: 0.1.18
Summary: SDK for interacting with Ignite Travel SOAP services, managing rooms, availability, inventory, and bookings.
Requires-Python: >=3.9
Requires-Dist: pydantic>=2.11.4
Requires-Dist: python-dateutil>=2.9.0.post0
Requires-Dist: python-dotenv>=1.1.0
Requires-Dist: requests>=2.32.3
